eq_d_c2.v
// File: eq_d_c2.v
// Generated by MyHDL 0.8
// Date: Tue Jun 10 09:06:52 2014


`timescale 1ns/10ps

module eq_d_c2 (
    d3,
    a2,
    clk,
    x2,
    x3,
    x4
);


output signed [18:0] d3;
reg signed [18:0] d3;
output signed [18:0] a2;
reg signed [18:0] a2;
input clk;
input signed [18:0] x2;
input signed [18:0] x3;
input signed [18:0] x4;






always @(posedge clk) begin: EQ_D_C2_EQ_LOGIC
    integer t2;
    integer t3;
    integer t1;
    t1 = (x2 + x4);
    t1 = $signed(t1 >>> 1);
    t2 = (x3 - t1);
    t1 = $signed(x4 >>> 2);
    t3 = ((x2 + t1) + t2);
    d3 <= t2;
    a2 <= t3;
end

endmodule

test_verilog/tb_eq_d_c2.v
module tb_eq_d_c2;

initial 
 begin
    $dumpfile("tb_eq_d_c2.vcd");
    $dumpvars(0,tb_eq_d_c2);
 end

/* Make a regular pulsing clock. */
  reg clk = 0;
  always #5 clk = !clk;

initial begin
     # 17 x2 = 4;
     # 15 x3 = 32;
     # 14 x4 = 66;

     # 19 x2 = 68;
     # 17 x3 = 19;
     # 16 x4 = 524283; 

     # 21 x2 = 524247;
     # 19 x3 = 4;
     # 18 x4 = 36; 

     # 30 x2 = 524246;
     # 28 x3 = 244;
     # 27 x4 = 164;

     # 40 x2 = 92;
     # 38 x3 = 116;
     # 37 x4 =  92;
     
     # 100 $stop;
end 
  
wire [18:0] d3;
wire [18:0] a2;

reg [18:0] x2;
reg [18:0] x3;
reg [18:0] x4;

 

eq_d_c2 dut(
    d3,
    a2,
    clk,
    x2,
    x3,
    x4
);

initial
     $monitor("At time %t, d3  = %h (%0d) ,a2  = %h (%0d)",
              $time, d3, d3,a2,a2);

 
endmodule

test_verilog/tb_eq_d_c2.vcd
$date
	Tue Jun 10 09:28:12 2014
$end
$version
	Icarus Verilog
$end
$timescale
	10ps
$end
$scope module tb_eq_d_c2 $end
$var wire 19 ! a2 [18:0] $end
$var wire 19 " d3 [18:0] $end
$var reg 1 # clk $end
$var reg 19 $ x2 [18:0] $end
$var reg 19 % x3 [18:0] $end
$var reg 19 & x4 [18:0] $end
$scope module dut $end
$var wire 1 ' clk $end
$var wire 19 ( x2 [18:0] $end
$var wire 19 ) x3 [18:0] $end
$var wire 19 * x4 [18:0] $end
$var reg 19 + a2 [18:0] $end
$var reg 19 , d3 [18:0] $end
$scope begin EQ_D_C2_EQ_LOGIC $end
$var integer 32 - t1 [31:0] $end
$var integer 32 . t2 [31:0] $end
$var integer 32 / t3 [31:0] $end
$upscope $end
$upscope $end
$upscope $end
$enddefinitions $end
#0
$dumpvars
bx /
bx .
bx -
bx ,
bx +
bx *
bx )
bx (
0'
bx &
bx %
bx $
0#
bx "
bx !
$end
#500
1#
1'
#1000
0#
0'
#1500
1#
1'
#1700
b100 $
b100 (
#2000
0#
0'
#2500
1#
1'
#3000
0#
0'
#3200
b100000 %
b100000 )
#3500
1#
1'
#4000
0#
0'
#4500
1#
1'
#4600
b1000010 &
b1000010 *
#5000
0#
0'
#5500
b10001 +
b10001 !
b1111111111111111101 ,
b1111111111111111101 "
b10001 /
b11111111111111111111111111111101 .
b10000 -
1#
1'
#6000
0#
0'
#6500
b110001 +
b110001 !
b1111111111111011101 ,
b1111111111111011101 "
b110001 /
b11111111111111111111111111011101 .
b10000 -
1#
1'
b1000100 $
b1000100 (
#7000
0#
0'
#7500
b10000 -
1#
1'
#8000
0#
0'
#8200
b10011 %
b10011 )
#8500
b100100 +
b100100 !
b1111111111111010000 ,
b1111111111111010000 "
b100100 /
b11111111111111111111111111010000 .
b10000 -
1#
1'
#9000
0#
0'
#9500
b10000 -
1#
1'
#9800
b1111111111111111011 &
b1111111111111111011 *
#10000
0#
0'
#10500
b110110 +
b110110 !
b1111111111111110100 ,
b1111111111111110100 "
b110110 /
b11111111111111111111111111110100 .
b11111111111111111111111111111110 -
1#
1'
#11000
0#
0'
#11500
b11111111111111111111111111111110 -
1#
1'
#11900
b1111111111111010111 $
b1111111111111010111 (
#12000
0#
0'
#12500
b1111111111111111111 +
b1111111111111111111 !
b101010 ,
b101010 "
b11111111111111111111111111111111 /
b101010 .
b11111111111111111111111111111110 -
1#
1'
#13000
0#
0'
#13500
b11111111111111111111111111111110 -
1#
1'
#13800
b100 %
b100 )
#14000
0#
0'
#14500
b1111111111111110000 +
b1111111111111110000 !
b11011 ,
b11011 "
b11111111111111111111111111110000 /
b11011 .
b11111111111111111111111111111110 -
1#
1'
#15000
0#
0'
#15500
b11111111111111111111111111111110 -
1#
1'
#15600
b100100 &
b100100 *
#16000
0#
0'
#16500
b1111111111111100111 +
b1111111111111100111 !
b111 ,
b111 "
b11111111111111111111111111100111 /
b111 .
b1001 -
1#
1'
#17000
0#
0'
#17500
b1001 -
1#
1'
#18000
0#
0'
#18500
b1001 -
1#
1'
#18600
b1111111111111010110 $
b1111111111111010110 (
#19000
0#
0'
#19500
b1111111111111100110 +
b1111111111111100110 !
b11111111111111111111111111100110 /
b1001 -
1#
1'
#20000
0#
0'
#20500
b1001 -
1#
1'
#21000
0#
0'
#21400
b11110100 %
b11110100 )
#21500
b11010110 +
b11010110 !
b11110111 ,
b11110111 "
b11010110 /
b11110111 .
b1001 -
1#
1'
#22000
0#
0'
#22500
b1001 -
1#
1'
#23000
0#
0'
#23500
b1001 -
1#
1'
#24000
0#
0'
#24100
b10100100 &
b10100100 *
#24500
b10110110 +
b10110110 !
b10110111 ,
b10110111 "
b10110110 /
b10110111 .
b101001 -
1#
1'
#25000
0#
0'
#25500
b101001 -
1#
1'
#26000
0#
0'
#26500
b101001 -
1#
1'
#27000
0#
0'
#27500
b101001 -
1#
1'
#28000
0#
0'
#28100
b1011100 $
b1011100 (
#28500
b11111001 +
b11111001 !
b1110100 ,
b1110100 "
b11111001 /
b1110100 .
b101001 -
1#
1'
#29000
0#
0'
#29500
b101001 -
1#
1'
#30000
0#
0'
#30500
b101001 -
1#
1'
#31000
0#
0'
#31500
b101001 -
1#
1'
#31900
b1110100 %
b1110100 )
#32000
0#
0'
#32500
b1111001 +
b1111001 !
b1111111111111110100 ,
b1111111111111110100 "
b1111001 /
b11111111111111111111111111110100 .
b101001 -
1#
1'
#33000
0#
0'
#33500
b101001 -
1#
1'
#34000
0#
0'
#34500
b101001 -
1#
1'
#35000
0#
0'
#35500
b101001 -
1#
1'
#35600
b1011100 &
b1011100 *
#36000
0#
0'
#36500
b10001011 +
b10001011 !
b11000 ,
b11000 "
b10001011 /
b11000 .
b10111 -
1#
1'
#37000
0#
0'
#37500
b10111 -
1#
1'
#38000
0#
0'
#38500
b10111 -
1#
1'
#39000
0#
0'
#39500
b10111 -
1#
1'
#40000
0#
0'
#40500
b10111 -
1#
1'
#41000
0#
0'
#41500
b10111 -
1#
1'
#42000
0#
0'
#42500
b10111 -
1#
1'
#43000
0#
0'
#43500
b10111 -
1#
1'
#44000
0#
0'
#44500
b10111 -
1#
1'
#45000
0#
0'
#45500
b10111 -
1#
1'
